lifter_api/__init__.py
lifter_api/__main__.py
lifter_api/main.py
lifter_api/utils/__init__.py
lifter_api/utils/decorators.py
lifter_api/utils/defaults.py
lifter_api/utils/exceptions.py
lifter_api/utils/helpers.py
lifter_api/utils/logging.py
lifter_api/utils/types.py
lifter_api_wrapper-0.4.0.dist-info/LICENSE
lifter_api_wrapper-0.4.0.dist-info/METADATA
lifter_api_wrapper-0.4.0.dist-info/WHEEL
lifter_api_wrapper-0.4.0.dist-info/top_level.txt
lifter_api_wrapper-0.4.0.dist-info/RECORD
