Metadata-Version: 2.1
Name: lifter-api-wrapper
Version: 0.4.0
Summary: A wrapper for Lifter API.
Author: Shivan Sivakumaran
Author-email: <shivan.sivakumaran@gmail.com>
License: MIT
Project-URL: homepage, https://github.com/WeightliftingNZ/lifter-api-wrapper
Project-URL: repository, https://github.com/WeightliftingNZ/lifter-api-wrapper
Project-URL: changelog, https://github.com/WeightliftingNZ/lifter-api-wrapper/blob/main/CHANGELOG.md
Project-URL: documentation, https://weightliftingnz.github.io/lifter-api-wrapper
Keywords: weightlifting,api wrapper
Classifier: License :: OSI Approved :: MIT License
Classifier: Development Status :: 4 - Beta
Classifier: Natural Language :: English
Classifier: Programming Language :: Python :: 3
Classifier: Programming Language :: Python :: 3.10
Classifier: Programming Language :: Python :: 3 :: Only
Classifier: Programming Language :: Python :: Implementation :: CPython
Requires-Python: >=3.10
License-File: LICENSE
Requires-Dist: requests
Requires-Dist: rich
